fastapi_jwt_auth/__init__.py
fastapi_jwt_auth/auth_config.py
fastapi_jwt_auth/auth_jwt.py
fastapi_jwt_auth/config.py
fastapi_jwt_auth/exceptions.py
tests/__init__.py
tests/conftest.py
tests/test_config.py
tests/test_cookies.py
tests/test_create_token.py
tests/test_decode_token.py
tests/test_denylist.py
tests/test_headers.py
tests/test_token_multiple_locations.py
tests/test_url_protected.py
tests/test_websocket.py
fastapi_jwt_auth_compat-1.0.1.dist-info/LICENSE
fastapi_jwt_auth_compat-1.0.1.dist-info/METADATA
fastapi_jwt_auth_compat-1.0.1.dist-info/WHEEL
fastapi_jwt_auth_compat-1.0.1.dist-info/top_level.txt
fastapi_jwt_auth_compat-1.0.1.dist-info/RECORD
