Metadata-Version: 2.1
Name: fastapi-jwt-auth-compat
Version: 1.0.1
Summary: A fork of the original fastapi-jwt-auth compatible with Pydantic 2.* versions
Home-page: https://github.com/jean-ek/fastapi-jwt-authV2
Author: jeanek
Author-email: jean.el.khoury08@gmail.com
Classifier: Programming Language :: Python :: 3
Classifier: License :: OSI Approved :: MIT License
Classifier: Operating System :: OS Independent
License-File: LICENSE
